{"stats":{"minecraft:picked_up":{"minecraft:campfire":1,"minecraft:respawn_anchor":3,"minecraft:red_bed":1},"minecraft:used":{"minecraft:respawn_anchor":2,"minecraft:campfire":1,"minecraft:red_bed":1},"minecraft:dropped":{"minecraft:campfire":1},"minecraft:custom":{"minecraft:jump":101,"minecraft:time_since_rest":59,"minecraft:damage_taken":280,"minecraft:walk_one_cm":82588,"minecraft:crouch_one_cm":2204,"minecraft:leave_game":23,"minecraft:sprint_one_cm":9851,"minecraft:play_time":29090,"minecraft:time_since_death":39,"minecraft:walk_on_water_one_cm":13,"minecraft:deaths":131,"minecraft:sleep_in_bed":3,"minecraft:sneak_time":607,"minecraft:total_world_time":29090,"minecraft:drop":1,"minecraft:fly_one_cm":31775,"minecraft:fall_one_cm":6627}},"DataVersion":2724}